nameko_amqp_retry/__init__.py
nameko_amqp_retry/backoff.py
nameko_amqp_retry/constants.py
nameko_amqp_retry/decorators.py
nameko_amqp_retry/events.py
nameko_amqp_retry/messaging.py
nameko_amqp_retry/rpc.py
nameko_amqp_retry-0.7.1.dist-info/LICENSE
nameko_amqp_retry-0.7.1.dist-info/METADATA
nameko_amqp_retry-0.7.1.dist-info/WHEEL
nameko_amqp_retry-0.7.1.dist-info/top_level.txt
nameko_amqp_retry-0.7.1.dist-info/zip-safe
nameko_amqp_retry-0.7.1.dist-info/RECORD
