Metadata-Version: 2.1
Name: nameko-amqp-retry
Version: 0.7.1
Summary: Nameko extension allowing AMQP entrypoints to retry later
Home-page: http://github.com/nameko/nameko-amqp-retry
Author: Student.com
License: Apache License, Version 2.0
Platform: UNKNOWN
Classifier: Programming Language :: Python
Classifier: Operating System :: MacOS :: MacOS X
Classifier: Operating System :: POSIX
Classifier: Programming Language :: Python :: 2
Classifier: Programming Language :: Python :: 2.7
Classifier: Programming Language :: Python :: 3
Classifier: Programming Language :: Python :: 3.3
Classifier: Programming Language :: Python :: 3.4
Classifier: Topic :: Internet
Classifier: Topic :: Software Development :: Libraries :: Python Modules
Classifier: Intended Audience :: Developers
Requires-Dist: nameko (>=2.7.0)
Requires-Dist: kombu
Provides-Extra: dev
Requires-Dist: arrow (==0.8.0) ; extra == 'dev'
Requires-Dist: coverage (==4.0.3) ; extra == 'dev'
Requires-Dist: flake8 (==2.5.0) ; extra == 'dev'
Requires-Dist: pylint (==1.5.1) ; extra == 'dev'
Requires-Dist: pytest (==2.8.3) ; extra == 'dev'
Provides-Extra: examples
Requires-Dist: arrow (==0.8.0) ; extra == 'examples'
